README.md
setup.py
metaquantome/__init__.py
metaquantome/cli.py
metaquantome.egg-info/PKG-INFO
metaquantome.egg-info/SOURCES.txt
metaquantome.egg-info/dependency_links.txt
metaquantome.egg-info/entry_points.txt
metaquantome.egg-info/requires.txt
metaquantome.egg-info/top_level.txt
metaquantome/classes/AnnotationHierarchy.py
metaquantome/classes/AnnotationNode.py
metaquantome/classes/SampleAnnotations.py
metaquantome/classes/SampleGroups.py
metaquantome/classes/__init__.py
metaquantome/data/__init__.py
metaquantome/data/test/__init__.py
metaquantome/data/test/make_test_data.py
metaquantome/databases/EnzymeDb.py
metaquantome/databases/GeneOntologyDb.py
metaquantome/databases/NCBITaxonomyDb.py
metaquantome/databases/__init__.py
metaquantome/databases/cog.py
metaquantome/modules/__init__.py
metaquantome/modules/db_download_handler.py
metaquantome/modules/expand.py
metaquantome/modules/filter.py
metaquantome/modules/function_taxonomy_interaction.py
metaquantome/modules/functional_analysis.py
metaquantome/modules/run_viz.py
metaquantome/modules/stat.py
metaquantome/modules/taxonomy_analysis.py
metaquantome/util/__init__.py
metaquantome/util/check_args.py
metaquantome/util/expand_io.py
metaquantome/util/stat_io.py
metaquantome/util/testutils.py
metaquantome/util/utils.py
tests/__init__.py
tests/notravis/__init__.py
tests/notravis/testDownloads.py
tests/travis/__init__.py
tests/travis/testAnnotationHierarchy.py
tests/travis/testAnnotationNode.py
tests/travis/testCLI.py
tests/travis/testEnzymeDb.py
tests/travis/testExpand.py
tests/travis/testFilter.py
tests/travis/testGeneOntologyDb.py
tests/travis/testIO.py
tests/travis/testNCBITaxonomyDb.py
tests/travis/testRunViz.py
tests/travis/testSampleAnnotations.py
tests/travis/testSampleGroups.py
tests/travis/testStat.py
tests/travis/testUtils.py