Metadata-Version: 1.2
Name: metaquantome
Version: 0.99.4a0
Summary: Quantitative metaproteomics analysis
Home-page: UNKNOWN
Author: Caleb Easterly
Author-email: caleb.easterly@gmail.com
License: Apache License 2.0
Project-URL: Bug Tracker, https://github.com/galaxyproteomics/metaquantome/issues
Project-URL: Source Code, https://github.com/galaxyproteomics/metaquantome
Platform: UNKNOWN
Classifier: Development Status :: 3 - Alpha
Classifier: License :: OSI Approved :: Apache Software License
Classifier: Operating System :: MacOS
Classifier: Operating System :: Unix
Classifier: Programming Language :: Python :: 3
Classifier: Topic :: Scientific/Engineering :: Bio-Informatics
Classifier: Intended Audience :: Science/Research
Requires-Python: >=3.5
